{
  "title": "Swift Teacher collaboration",
  "subtitle": "Various learning materials created for Swift Playgrounds",
  "publisherName": "Daniel Budd",
  "feedIdentifier": "io.github.swiftteacher",
  "contactURL": "mailto:contact@danielbudd.com.au",
  "formatVersion": "1.0",
  "documents": [
    {
      "title": "Geometry",
      "overviewSubtitle": "Geometry with Swift Playgrounds",
      "detailSubtitle": "Learn to code with visual problems!",
      "description": "In this course students will learn the fundamentals of Swift using Geometry as their context for learning. The Playground resembles Logo, which is an educational visual simulation designed by Seymour Papert and the team at MIT.",
      "difficultyLevel": "beginner",
      "contentIdentifier": "io.github.dbbudd.Geometry",
      "contentVersion": "2.0",
      "url": "https://dbbudd.github.io/Geometry/Geometry.playgroundbook.zip",
      "publishedDate": "2018-06-25T12:00:00+00:00",
      "lastUpdatedDate": "2018-06-26T12:00:00+00:00",
      "bannerImageURL": "https://dbbudd.github.io/Geometry/banner_2x.png",
      "thumbnailURL": "https://dbbudd.github.io/Geometry/geometry_2x.png",
      "additionalInformation": [
        {
          "name": "Languages",
          "value": "English"
        }
      ],
      "previewImageURLs": [
        "https://dbbudd.github.io/Geometry/preview-1.png",
        "https://dbbudd.github.io/Geometry/preview-2.png",
        "https://dbbudd.github.io/Geometry/preview-3.png"
      ]
    }
  ]
}
